pytest_failed_screenshot_allure.py
setup.py
pytest_ui_failed_screenshot_allure.egg-info/PKG-INFO
pytest_ui_failed_screenshot_allure.egg-info/SOURCES.txt
pytest_ui_failed_screenshot_allure.egg-info/dependency_links.txt
pytest_ui_failed_screenshot_allure.egg-info/entry_points.txt
pytest_ui_failed_screenshot_allure.egg-info/requires.txt
pytest_ui_failed_screenshot_allure.egg-info/top_level.txt